a2y_matplot.cp38-win32.pyd
a2y_matplot-0.8.2.dist-info/LICENSE
a2y_matplot-0.8.2.dist-info/METADATA
a2y_matplot-0.8.2.dist-info/WHEEL
a2y_matplot-0.8.2.dist-info/top_level.txt
a2y_matplot-0.8.2.dist-info/RECORD
